{
  "active": true,
  "sortOrder": 6,
  "title": "Standard F1B Goldendoodles (River)",
  "slug": "f1bgoldendoodles-river",
  "breeder": "Luke & Eli Yarnelle",
  "generation": "F1B",
  "priceRange": "$1,800 - $2,000",
  "litterTitle": "River x Festus",
  "dateOfBirth": "April 27, 2026",
  "takeHomeDate": "June 22, 2026",
  "estimatedSize": "45-60 lbs",
  "grooming": "Roughly every 3-4 months",
  "temperament": "smart, playful, sweet, love to cuddle, incredibly friendly with other dogs, cats, and kiddos",
  "deposit": "$600",
  "contact": "Eli · (260) 445-4378",
  "damName": "River",
  "damDesc": "Standard F1 Goldendoodle (45lbs)",
  "damPhoto": "https://pub-e847384c23164145a930ab957dbde017.r2.dev/River pic.jpeg",
  "sireName": "Festus",
  "sireDesc": "AKC Red Standard Poodle (60lbs)",
  "cardDesc": "Our family-raised Standard F1b Goldendoodles, born to our sweet F1 Goldendoodle mom, River, and handsome AKC Standard Poodle dad, Festus, are the perfect addition to any vibrant home. Raised with focused care on our family farm, these intelligent, affectionate puppies are beautifully socialized, confident, and ready for a lifetime of love with your family.",
  "cardPhoto": "https://pub-e847384c23164145a930ab957dbde017.r2.dev/Goldendoodle%20Riley.JPG",
  "sirePhoto": "https://pub-e847384c23164145a930ab957dbde017.r2.dev/Festus pic.jpeg",
  "puppies": [
    {
      "name": "Ricky",
      "gender": "Boy",
      "price": "$1,800",
      "status": "Available",
      "photos": [
        {
          "src": "https://pub-e847384c23164145a930ab957dbde017.r2.dev/Goldedoodle Ricky.JPG",
          "alt": "Goldendoodles in Indiana"
        }
      ]
    },
    {
      "name": "Robert",
      "gender": "Boy",
      "price": "$1,800",
      "status": "Available",
      "photos": [
        {
          "src": "https://pub-e847384c23164145a930ab957dbde017.r2.dev/Goldendoodle Robert.JPG",
          "alt": "Goldendoodles in Indiana"
        }
      ]
    },
    {
      "name": "Reese",
      "gender": "Boy",
      "price": "$1,800",
      "status": "Reserved"
    },
    {
      "name": "Russel",
      "gender": "Boy",
      "price": "$1,800",
      "status": "Available",
      "photos": [
        {
          "src": "https://pub-e847384c23164145a930ab957dbde017.r2.dev/Goldendoodle Russel.JPG",
          "alt": "Goldendoodles in Indiana"
        }
      ]
    },
    {
      "name": "Rip",
      "gender": "Boy",
      "price": "$1,800",
      "status": "Available",
      "photos": [
        {
          "src": "https://pub-e847384c23164145a930ab957dbde017.r2.dev/Goldendoodle Rip.JPG",
          "alt": "Goldendoodles in Indiana"
        }
      ]
    },
    {
      "name": "Ruby",
      "gender": "Girl",
      "price": "$2,000",
      "status": "Available",
      "photos": [
        {
          "src": "https://pub-e847384c23164145a930ab957dbde017.r2.dev/Goldendoodle Ruby.JPG",
          "alt": "Goldendoodles in Indiana"
        }
      ]
    },
    {
      "name": "Remi",
      "gender": "Girl",
      "price": "$2,000",
      "status": "Available",
      "photos": [
        {
          "src": "https://pub-e847384c23164145a930ab957dbde017.r2.dev/Goldendoodle remi.JPG",
          "alt": "Goldendoodles in Indiana"
        }
      ]
    },
    {
      "name": "Riley",
      "gender": "Girl",
      "price": "$2,000",
      "status": "Available",
      "photos": [
        {
          "src": "https://pub-e847384c23164145a930ab957dbde017.r2.dev/Goldendoodle Riley.JPG",
          "alt": "Goldendoodles in Indiana"
        }
      ]
    }
  ],
  "showCarousel": true,
  "previousPuppies": [
    {
      "src": "https://pub-e847384c23164145a930ab957dbde017.r2.dev/River x Festus puppies.jpeg",
      "alt": "Standard goldendoodles in Indiana"
    }
  ]
}